.coveragerc
.editorconfig
.travis.yml
CHANGES.rst
CONTRIBUTORS.rst
DEVELOP.rst
LICENSE.GPL
LICENSE.rst
MANIFEST.in
README.rst
base.cfg
bobtemplate.cfg
buildout.cfg
constraints.txt
constraints_plone43.txt
constraints_plone50.txt
constraints_plone51.txt
constraints_plone52.txt
requirements.txt
setup.cfg
setup.py
test_plone43.cfg
test_plone50.cfg
test_plone51.cfg
test_plone52.cfg
tox.ini
docs/conf.py
docs/index.rst
src/collective/__init__.py
src/collective.metadataaudit.egg-info/PKG-INFO
src/collective.metadataaudit.egg-info/SOURCES.txt
src/collective.metadataaudit.egg-info/dependency_links.txt
src/collective.metadataaudit.egg-info/entry_points.txt
src/collective.metadataaudit.egg-info/namespace_packages.txt
src/collective.metadataaudit.egg-info/not-zip-safe
src/collective.metadataaudit.egg-info/requires.txt
src/collective.metadataaudit.egg-info/top_level.txt
src/collective/metadataaudit/__init__.py
src/collective/metadataaudit/configure.zcml
src/collective/metadataaudit/interfaces.py
src/collective/metadataaudit/permissions.zcml
src/collective/metadataaudit/setuphandlers.py
src/collective/metadataaudit/testing.py
src/collective/metadataaudit/browser/__init__.py
src/collective/metadataaudit/browser/configure.zcml
src/collective/metadataaudit/browser/overrides/.gitkeep
src/collective/metadataaudit/browser/static/.gitkeep
src/collective/metadataaudit/locales/README.rst
src/collective/metadataaudit/locales/__init__.py
src/collective/metadataaudit/locales/collective.metadataaudit.pot
src/collective/metadataaudit/locales/update.py
src/collective/metadataaudit/locales/update.sh
src/collective/metadataaudit/locales/en/LC_MESSAGES/collective.metadataaudit.mo
src/collective/metadataaudit/locales/en/LC_MESSAGES/collective.metadataaudit.po
src/collective/metadataaudit/profiles/default/browserlayer.xml
src/collective/metadataaudit/profiles/default/catalog.xml
src/collective/metadataaudit/profiles/default/metadata.xml
src/collective/metadataaudit/profiles/default/rolemap.xml
src/collective/metadataaudit/profiles/default/registry/main.xml
src/collective/metadataaudit/profiles/uninstall/browserlayer.xml
src/collective/metadataaudit/subscribers/__init__.py
src/collective/metadataaudit/subscribers/configure.zcml
src/collective/metadataaudit/subscribers/content.py
src/collective/metadataaudit/tests/__init__.py
src/collective/metadataaudit/tests/test_robot.py
